Workbook

Sheet Database
B2: Database
B4: Date | C4: Eomonth | D4: Year | E4: Region | F4: Product | G4: Revenue | H4: Cost | I4: Units Sold | J4: Customer Satisfaction | K4: Profit
B5: 43831 | C5: =EOMONTH(B5,0) -> 43861 | D5: =YEAR(B5) -> 2020 | E5: South America | F5: Product B | G5: 7284.69 | H5: 2198.7 | I5: 89 | J5: 3.42 | K5: =G5-H5 -> 5085.99
B6: 43832 | C6: =EOMONTH(B6,0) -> 43861 | D6: =YEAR(B6) -> 2020 | E6: Australia | F6: Product D | G6: 5808.37 | H6: 2775.12 | I6: 67 | J6: 4.63 | K6: =G6-H6 -> 3033.25
B7: 43833 | C7: =EOMONTH(B7,0) -> 43861 | D7: =YEAR(B7) -> 2020 | E7: Asia | F7: Product D | G7: 3444.13 | H7: 4438.15 | I7: 64 | J7: 1.96 | K7: =G7-H7 -> -994.02
B8: 43834 | C8: =EOMONTH(B8,0) -> 43861 | D8: =YEAR(B8) -> 2020 | E8: Australia | F8: Product A | G8: 4714.49 | H8: 3512.67 | I8: 13 | J8: 2.88 | K8: =G8-H8 -> 1201.82
B9: 43835 | C9: =EOMONTH(B9,0) -> 43861 | D9: =YEAR(B9) -> 2020 | E9: Australia | F9: Product B | G9: 3686.57 | H9: 2543.06 | I9: 33 | J9: 2.8 | K9: =G9-H9 -> 1143.51
B10: 43836 | C10: =EOMONTH(B10,0) -> 43861 | D10: =YEAR(B10) -> 2020 | E10: Europe | F10: Product A | G10: 2925.8 | H10: 3458.07 | I10: 43 | J10: 2.89 | K10: =G10-H10 -> -532.27
B11: 43837 | C11: =EOMONTH(B11,0) -> 43861 | D11: =YEAR(B11) -> 2020 | E11: Asia | F11: Product C | G11: 6389.27 | H11: 4119.48 | I11: 39 | J11: 3.49 | K11: =G11-H11 -> 2269.79
B12: 43838 | C12: =EOMONTH(B12,0) -> 43861 | D12: =YEAR(B12) -> 2020 | E12: Asia | F12: Product C | G12: 7864.12 | H12: 3739.71 | I12: 91 | J12: 2.88 | K12: =G12-H12 -> 4124.41
B13: 43839 | C13: =EOMONTH(B13,0) -> 43861 | D13: =YEAR(B13) -> 2020 | E13: Asia | F13: Product A | G13: 2902.15 | H13: 3047.7 | I13: 28 | J13: 2.79 | K13: =G13-H13 -> -145.55
B14: 43840 | C14: =EOMONTH(B14,0) -> 43861 | D14: =YEAR(B14) -> 2020 | E14: Australia | F14: Product D | G14: 5844.45 | H14: 2482.45 | I14: 40 | J14: 2.9 | K14: =G14-H14 -> 3362
B15: 43841 | C15: =EOMONTH(B15,0) -> 43861 | D15: =YEAR(B15) -> 2020 | E15: South America | F15: Product D | G15: 4024.04 | H15: 3558.58 | I15: 69 | J15: 3.36 | K15: =G15-H15 -> 465.46
B16: 43842 | C16: =EOMONTH(B16,0) -> 43861 | D16: =YEAR(B16) -> 2020 | E16: Asia | F16: Product A | G16: 4269.31 | H16: 3314.79 | I16: 69 | J16: 3.15 | K16: =G16-H16 -> 954.52
... B504: 44330 | C504: =EOMONTH(B504,0) -> 44347 | D504: =YEAR(B504) -> 2021 | E504: North America | F504: Product B | G504: 3977.02 | H504: 3147.64 | I504: 21 | J504: 1.55 | K504: =G504-H504 -> 829.38

Sheet Analysis-->
B14: Analysis-->

Sheet Analysis
C2: 1. Trend Analysis
C4: in$ | D4: 43861 | E4: 43890 | F4: 43921 | G4: 43951 | H4: 43982 | I4: 44012 | J4: 44043 | K4: 44074 | L4: 44104 | M4: 44135 | N4: 44165 | O4: 44196 | P4: 44227 | Q4: 44255 | R4: 44286 | S4: 44316 | T4: 44347
C5: Revenue | D5: =SUMIF(Database!$C:$C,Analysis!D$4,Database!$G:$G) -> 147266.78 | E5: =SUMIF(Database!$C:$C,Analysis!E$4,Database!$G:$G) -> 133231.25 | F5: =SUMIF(Database!$C:$C,Analysis!F$4,Database!$G:$G) -> 157272.6 | G5: =SUMIF(Database!$C:$C,Analysis!G$4,Database!$G:$G) -> 154169.84 | H5: =SUMIF(Database!$C:$C,Analysis!H$4,Database!$G:$G) -> 154464.4 | I5: =SUMIF(Database!$C:$C,Analysis!I$4,Database!$G:$G) -> 143474.97 | J5: =SUMIF(Database!$C:$C,Analysis!J$4,Database!$G:$G) -> 153576.08 | K5: =SUMIF(Database!$C:$C,Analysis!K$4,Database!$G:$G) -> 154907.94 | ... T5: =SUMIF(Database!$C:$C,Analysis!T$4,Database!$G:$G) -> 67688.15
C6: Cogs | D6: =SUMIF(Database!$C:$C,Analysis!D$4,Database!$H:$H) -> 103902.67 | E6: =SUMIF(Database!$C:$C,Analysis!E$4,Database!$H:$H) -> 90529.2 | F6: =SUMIF(Database!$C:$C,Analysis!F$4,Database!$H:$H) -> 90780.12 | G6: =SUMIF(Database!$C:$C,Analysis!G$4,Database!$H:$H) -> 93536.83 | H6: =SUMIF(Database!$C:$C,Analysis!H$4,Database!$H:$H) -> 102390.34 | I6: =SUMIF(Database!$C:$C,Analysis!I$4,Database!$H:$H) -> 91311.8 | J6: =SUMIF(Database!$C:$C,Analysis!J$4,Database!$H:$H) -> 88655.21 | K6: =SUMIF(Database!$C:$C,Analysis!K$4,Database!$H:$H) -> 97193.21 | ... T6: =SUMIF(Database!$C:$C,Analysis!T$4,Database!$H:$H) -> 42814.83
C11: Trend Analysis | J11: Comparative Analysis
L13: 2020 | M13: 2020 | N13: 2020 | O13: 2020 | P13: 2020
J14: in$ | L14: South America | M14: Australia | N14: Asia | O14: Europe | P14: North America
J15: Revenue | L15: =+SUMIFS(Database!$G:$G,Database!$D:$D,Analysis!L$13,Database!$E:$E,Analysis!L$14) -> 420713.78 | M15: =+SUMIFS(Database!$G:$G,Database!$D:$D,Analysis!M$13,Database!$E:$E,Analysis!M$14) -> 297196.72 | N15: =+SUMIFS(Database!$G:$G,Database!$D:$D,Analysis!N$13,Database!$E:$E,Analysis!N$14) -> 383940.06 | O15: =+SUMIFS(Database!$G:$G,Database!$D:$D,Analysis!O$13,Database!$E:$E,Analysis!O$14) -> 330788.18 | P15: =+SUMIFS(Database!$G:$G,Database!$D:$D,Analysis!P$13,Database!$E:$E,Analysis!P$14) -> 389656.21
J16: Cogs | L16: =+SUMIFS(Database!$H:$H,Database!$D:$D,Analysis!L$13,Database!$E:$E,Analysis!L$14) -> 252096.6 | M16: =+SUMIFS(Database!$H:$H,Database!$D:$D,Analysis!M$13,Database!$E:$E,Analysis!M$14) -> 182392.55 | N16: =+SUMIFS(Database!$H:$H,Database!$D:$D,Analysis!N$13,Database!$E:$E,Analysis!N$14) -> 231265.04 | O16: =+SUMIFS(Database!$H:$H,Database!$D:$D,Analysis!O$13,Database!$E:$E,Analysis!O$14) -> 195286.25 | P16: =+SUMIFS(Database!$H:$H,Database!$D:$D,Analysis!P$13,Database!$E:$E,Analysis!P$14) -> 256312.6
J17: Profit | L17: =+SUMIFS(Database!$K:$K,Database!$D:$D,Analysis!L$13,Database!$E:$E,Analysis!L$14) -> 168617.18 | M17: =+SUMIFS(Database!$K:$K,Database!$D:$D,Analysis!M$13,Database!$E:$E,Analysis!M$14) -> 114804.17 | N17: =+SUMIFS(Database!$K:$K,Database!$D:$D,Analysis!N$13,Database!$E:$E,Analysis!N$14) -> 152675.02 | O17: =+SUMIFS(Database!$K:$K,Database!$D:$D,Analysis!O$13,Database!$E:$E,Analysis!O$14) -> 135501.93 | P17: =+SUMIFS(Database!$K:$K,Database!$D:$D,Analysis!P$13,Database!$E:$E,Analysis!P$14) -> 133343.61
J18: Profit Percentage | L18: =L17/L15 -> 0.40078835 | M18: =M17/M15 -> 0.38629016 | N18: =N17/N15 -> 0.39765327 | O18: =O17/O15 -> 0.40963353 | P18: =P17/P15 -> 0.34220835
L22: 2021 | M22: 2021 | N22: 2021 | O22: 2021 | P22: 2021
J23: in$ | L23: South America | M23: Australia | N23: Asia | O23: Europe | P23: North America
J24: Revenue | L24: =+SUMIFS(Database!$G:$G,Database!$D:$D,Analysis!L$22,Database!$E:$E,Analysis!L$23) -> 130651.33 | M24: =+SUMIFS(Database!$G:$G,Database!$D:$D,Analysis!M$22,Database!$E:$E,Analysis!M$23) -> 165671.4 | N24: =+SUMIFS(Database!$G:$G,Database!$D:$D,Analysis!N$22,Database!$E:$E,Analysis!N$23) -> 108894.22 | O24: =+SUMIFS(Database!$G:$G,Database!$D:$D,Analysis!O$22,Database!$E:$E,Analysis!O$23) -> 161321.93 | P24: =+SUMIFS(Database!$G:$G,Database!$D:$D,Analysis!P$22,Database!$E:$E,Analysis!P$23) -> 131163.92
J25: Cogs | L25: =+SUMIFS(Database!$H:$H,Database!$D:$D,Analysis!L$22,Database!$E:$E,Analysis!L$23) -> 86264.37 | M25: =+SUMIFS(Database!$H:$H,Database!$D:$D,Analysis!M$22,Database!$E:$E,Analysis!M$23) -> 96159.31 | N25: =+SUMIFS(Database!$H:$H,Database!$D:$D,Analysis!N$22,Database!$E:$E,Analysis!N$23) -> 58521.57 | O25: =+SUMIFS(Database!$H:$H,Database!$D:$D,Analysis!O$22,Database!$E:$E,Analysis!O$23) -> 96404.93 | P25: =+SUMIFS(Database!$H:$H,Database!$D:$D,Analysis!P$22,Database!$E:$E,Analysis!P$23) -> 82868.61
J26: Profit | L26: =+SUMIFS(Database!$K:$K,Database!$D:$D,Analysis!L$22,Database!$E:$E,Analysis!L$23) -> 44386.96 | M26: =+SUMIFS(Database!$K:$K,Database!$D:$D,Analysis!M$22,Database!$E:$E,Analysis!M$23) -> 69512.09 | N26: =+SUMIFS(Database!$K:$K,Database!$D:$D,Analysis!N$22,Database!$E:$E,Analysis!N$23) -> 50372.65 | O26: =+SUMIFS(Database!$K:$K,Database!$D:$D,Analysis!O$22,Database!$E:$E,Analysis!O$23) -> 64917 | P26: =+SUMIFS(Database!$K:$K,Database!$D:$D,Analysis!P$22,Database!$E:$E,Analysis!P$23) -> 48295.31
J27: Profit Percentage | L27: =L26/L24 -> 0.339736 | M27: =M26/M24 -> 0.41957809 | N27: =N26/N24 -> 0.46258332 | O27: =O26/O24 -> 0.40240654 | P27: =P26/P24 -> 0.36820575
J31: Region | K31: Total Revenue | L31: Total Profit | M31: % Profit
C32: Product | D32: Total Revenue | E32: Total Profit | F32: % Profit | J32: Asia | K32: 492834.28 | L32: 203047.67 | M32: 0.20667988
C33: Product A | D33: 728198.58 | E33: 287535.44 | F33: 0.292679 | J33: Australia | K33: 462868.12 | L33: 184316.26 | M33: 0.18761339
C34: Product B | D34: 636112.12 | E34: 246036 | F34: 0.2504372 | J34: Europe | K34: 492110.11 | L34: 200418.93 | M34: 0.20400411
C35: Product C | D35: 643812.02 | E35: 269817.18 | F35: 0.27464379 | J35: North America | K35: 520820.13 | L35: 181638.92 | M35: 0.18488816
C36: Product D | D36: 511875.03 | E36: 179037.3 | F36: 0.18224 | J36: South America | K36: 551365.11 | L36: 213004.14 | M36: 0.21681445
C37: Grand Total | D37: 2519997.7 | E37: 982425.92 | F37: 1 | J37: Grand Total | K37: 2519997.8 | L37: 982425.92 | M37: 1
E40: 2020-2021 Sales by Region | L40: 2020-2021 Sales by Product

Sheet Correlation Analysis
B4: Revenue | C4: Cost | D4: Correlation | G4: Revenue | H4: Units Sold | I4: Correlation | M4: Revenue | N4: Customer Satisfaction | O4: Correlation
B5: 7284.69 | C5: 2198.7 | D5: =CORREL(B:B,C:C) -> 0.065012104 | G5: 7284.69 | H5: 89 | I5: =CORREL(G:G,H:H) -> 0.038053358 | M5: 7284.69 | N5: 3.42 | O5: =CORREL(M:M,N:N) -> 0.029514504
B6: 5808.37 | C6: 2775.12 | D6: =CORREL(B:B,C:C) -> 0.065012104 | G6: 5808.37 | H6: 67 | I6: =CORREL(G:G,H:H) -> 0.038053358 | M6: 5808.37 | N6: 4.63 | O6: =CORREL(M:M,N:N) -> 0.029514504
B7: 3444.13 | C7: 4438.15 | D7: =CORREL(B:B,C:C) -> 0.065012104 | G7: 3444.13 | H7: 64 | I7: =CORREL(G:G,H:H) -> 0.038053358 | M7: 3444.13 | N7: 1.96 | O7: =CORREL(M:M,N:N) -> 0.029514504
B8: 4714.49 | C8: 3512.67 | D8: =CORREL(B:B,C:C) -> 0.065012104 | G8: 4714.49 | H8: 13 | I8: =CORREL(G:G,H:H) -> 0.038053358 | M8: 4714.49 | N8: 2.88 | O8: =CORREL(M:M,N:N) -> 0.029514504
B9: 3686.57 | C9: 2543.06 | D9: =CORREL(B:B,C:C) -> 0.065012104 | G9: 3686.57 | H9: 33 | I9: =CORREL(G:G,H:H) -> 0.038053358 | M9: 3686.57 | N9: 2.8 | O9: =CORREL(M:M,N:N) -> 0.029514504
B10: 2925.8 | C10: 3458.07 | D10: =CORREL(B:B,C:C) -> 0.065012104 | G10: 2925.8 | H10: 43 | I10: =CORREL(G:G,H:H) -> 0.038053358 | M10: 2925.8 | N10: 2.89 | O10: =CORREL(M:M,N:N) -> 0.029514504
B11: 6389.27 | C11: 4119.48 | D11: =CORREL(B:B,C:C) -> 0.065012104 | G11: 6389.27 | H11: 39 | I11: =CORREL(G:G,H:H) -> 0.038053358 | M11: 6389.27 | N11: 3.49 | O11: =CORREL(M:M,N:N) -> 0.029514504
B12: 7864.12 | C12: 3739.71 | D12: =CORREL(B:B,C:C) -> 0.065012104 | G12: 7864.12 | H12: 91 | I12: =CORREL(G:G,H:H) -> 0.038053358 | M12: 7864.12 | N12: 2.88 | O12: =CORREL(M:M,N:N) -> 0.029514504
B13: 2902.15 | C13: 3047.7 | D13: =CORREL(B:B,C:C) -> 0.065012104 | G13: 2902.15 | H13: 28 | I13: =CORREL(G:G,H:H) -> 0.038053358 | M13: 2902.15 | N13: 2.79 | O13: =CORREL(M:M,N:N) -> 0.029514504
B14: 5844.45 | C14: 2482.45 | D14: =CORREL(B:B,C:C) -> 0.065012104 | G14: 5844.45 | H14: 40 | I14: =CORREL(G:G,H:H) -> 0.038053358 | M14: 5844.45 | N14: 2.9 | O14: =CORREL(M:M,N:N) -> 0.029514504
B15: 4024.04 | C15: 3558.58 | D15: =CORREL(B:B,C:C) -> 0.065012104 | G15: 4024.04 | H15: 69 | I15: =CORREL(G:G,H:H) -> 0.038053358 | M15: 4024.04 | N15: 3.36 | O15: =CORREL(M:M,N:N) -> 0.029514504
B16: 4269.31 | C16: 3314.79 | D16: =CORREL(B:B,C:C) -> 0.065012104 | G16: 4269.31 | H16: 69 | I16: =CORREL(G:G,H:H) -> 0.038053358 | M16: 4269.31 | N16: 3.15 | O16: =CORREL(M:M,N:N) -> 0.029514504
... B504: 3977.02 | C504: 3147.64 | D504: =CORREL(B:B,C:C) -> 0.065012104 | G504: 3977.02 | H504: 21 | I504: =CORREL(G:G,H:H) -> 0.038053358 | M504: 3977.02 | N504: 1.55 | O504: =CORREL(M:M,N:N) -> 0.029514504

Sheet Time Series
B2: Database | Q2: Database
B4: Date | C4: Revenue | D4: Revenue (t-1) | F4: SUMMARY OUTPUT | Q4: Date | R4: Revenue | S4: Revenue (t-12)
B5: 43831 | C5: 7284.69 | Q5: 43831 | R5: 7284.69
B6: 43832 | C6: 5808.37 | D6: 7284.69 | F6: Regression Statistics | Q6: 43832 | R6: 5808.37
B7: 43833 | C7: 3444.13 | D7: 5808.37 | F7: Multiple R | G7: 0.0090678613 | Q7: 43833 | R7: 3444.13
B8: 43834 | C8: 4714.49 | D8: 3444.13 | F8: R Square | G8: 8.2226109e-05 | Q8: 43834 | R8: 4714.49
B9: 43835 | C9: 3686.57 | D9: 4714.49 | F9: Adjusted R Square | G9: -0.0019296809 | Q9: 43835 | R9: 3686.57
B10: 43836 | C10: 2925.8 | D10: 3686.57 | F10: Standard Error | G10: 1468.2352 | Q10: 43836 | R10: 2925.8
B11: 43837 | C11: 6389.27 | D11: 2925.8 | F11: Observations | G11: 499 | Q11: 43837 | R11: 6389.27
B12: 43838 | C12: 7864.12 | D12: 6389.27 | Q12: 43838 | R12: 7864.12
B13: 43839 | C13: 2902.15 | D13: 7864.12 | F13: ANOVA | Q13: 43839 | R13: 2902.15
B14: 43840 | C14: 5844.45 | D14: 2902.15 | G14: df | H14: SS | I14: MS | J14: F | K14: Significance F | Q14: 43840 | R14: 5844.45
B15: 43841 | C15: 4024.04 | D15: 5844.45 | F15: Regression | G15: 1 | H15: 88103.485 | I15: 88103.485 | J15: 0.040869737 | K15: 0.8398723 | Q15: 43841 | R15: 4024.04
B16: 43842 | C16: 4269.31 | D16: 4024.04 | F16: Residual | G16: 497 | H16: 1.0713901e+09 | I16: 2155714.5 | Q16: 43842 | R16: 4269.31 | S16: 7284.69
B17: 43843 | C17: 4111.41 | D17: 4269.31 | F17: Total | G17: 498 | H17: 1.0714782e+09 | Q17: 43843 | R17: 4111.41 | S17: 5808.37
B18: 43844 | C18: 3704.01 | D18: 4111.41 | Q18: 43844 | R18: 3704.01 | S18: 3444.13
B19: 43845 | C19: 5072.78 | D19: 3704.01 | G19: Coefficients | H19: Standard Error | I19: t Stat | J19: P-value | K19: Lower 95% | L19: Upper 95% | M19: Lower 95.0% | N19: Upper 95.0% | Q19: 43845 | R19: 5072.78 | S19: 4714.49
B20: 43846 | C20: 3753.57 | D20: 5072.78 | F20: Intercept | G20: 5081.1351 | H20: 235.12244 | I20: 21.610592 | J20: 1.6197129e-73 | K20: 4619.1786 | L20: 5543.0916 | M20: 4619.1786 | N20: 5543.0916 | Q20: 43846 | R20: 3753.57 | S20: 3686.57
B21: 43847 | C21: 5405.69 | D21: 3753.57 | F21: X Variable 1 | G21: -0.0090513337 | H21: 0.044772532 | I21: -0.20216265 | J21: 0.8398723 | K21: -0.097018105 | L21: 0.078915437 | M21: -0.097018105 | N21: 0.078915437 | Q21: 43847 | R21: 5405.69 | S21: 2925.8
B22: 43848 | C22: 4924.64 | D22: 5405.69 | Q22: 43848 | R22: 4924.64 | S22: 6389.27
B23: 43849 | C23: 4641.58 | D23: 4924.64 | Q23: 43849 | R23: 4641.58 | S23: 7864.12
B24: 43850 | C24: 3638.65 | D24: 4641.58 | Q24: 43850 | R24: 3638.65 | S24: 2902.15
B25: 43851 | C25: 4134.84 | D25: 3638.65 | Q25: 43851 | R25: 4134.84 | S25: 5844.45
B26: 43852 | C26: 6133.09 | D26: 4134.84 | Q26: 43852 | R26: 6133.09 | S26: 4024.04
B27: 43853 | C27: 5751.38 | D27: 6133.09 | Q27: 43853 | R27: 5751.38 | S27: 4269.31
B28: 43854 | C28: 3533.67 | D28: 5751.38 | Q28: 43854 | R28: 3533.67 | S28: 4111.41
B29: 43855 | C29: 5149 | D29: 3533.67 | Q29: 43855 | R29: 5149 | S29: 3704.01
B30: 43856 | C30: 6127.08 | D30: 5149 | Q30: 43856 | R30: 6127.08 | S30: 5072.78
B31: 43857 | C31: 2495.89 | D31: 6127.08 | Q31: 43857 | R31: 2495.89 | S31: 3753.57
B32: 43858 | C32: 5815.04 | D32: 2495.89 | Q32: 43858 | R32: 5815.04 | S32: 5405.69
B33: 43859 | C33: 4006.06 | D33: 5815.04 | Q33: 43859 | R33: 4006.06 | S33: 4924.64
... B504: 44330 | C504: 3977.02 | D504: 4629.23 | Q504: 44330 | R504: 3977.02 | S504: 3549.54
